td/client.py
td/credentials.py
td/session.py
td/rest/accounts.py
td/rest/instruments.py
td/rest/market_hours.py
td/rest/movers.py
td/rest/options_chain.py
td/rest/orders.py
td/rest/price_history.py
td/rest/quotes.py
td/rest/saved_orders.py
td/rest/user_info.py
td/rest/watchlists.py
td/streaming/client.py
td/streaming/services.py
td/utils/enums.py
td/utils/option_chain.py
td/utils/orders.py
td/utils/user_preferences.py
py_tda_api-0.1.3.dist-info/LICENSE
py_tda_api-0.1.3.dist-info/METADATA
py_tda_api-0.1.3.dist-info/WHEEL
py_tda_api-0.1.3.dist-info/top_level.txt
py_tda_api-0.1.3.dist-info/RECORD
