Metadata-Version: 2.1
Name: py-tda-api
Version: 0.1.3
Summary: A python client lirbary for the TD Ameritrade API.
Home-page: https://github.com/areed1192/td-ameritrade-api
Author: Alex Reed
Author-email: coding.sigma@gmail.com
Keywords: finance,td ameritrade,api
Classifier: Development Status :: 3 - Alpha
Classifier: Intended Audience :: Financial and Insurance Industry
Classifier: License :: OSI Approved :: MIT License
Classifier: Natural Language :: English
Classifier: Operating System :: OS Independent
Classifier: Programming Language :: Python :: 3
Requires-Python: >=3.8
License-File: LICENSE
Requires-Dist: requests (>=2.24.0)
Requires-Dist: dataclasses (>=0.6)
Requires-Dist: websockets (>=9.1)
